setup.cfg
setup.py
kbn/__init__.py
kbn/kbn.py
kbn.egg-info/PKG-INFO
kbn.egg-info/SOURCES.txt
kbn.egg-info/dependency_links.txt
kbn.egg-info/not-zip-safe
kbn.egg-info/top_level.txt