Metadata-Version: 1.0
Name: kbn
Version: 0.0
Summary: game for everyone
Home-page: UNKNOWN
Author: UNKNOWN
Author-email: kseniya.shtv.98@gmail.com
License: UNKNOWN
Platform: UNKNOWN
